nwkfmt/cli.py
nwkfmt-0.4.1.dist-info/LICENSE
nwkfmt-0.4.1.dist-info/METADATA
nwkfmt-0.4.1.dist-info/WHEEL
nwkfmt-0.4.1.dist-info/entry_points.txt
nwkfmt-0.4.1.dist-info/RECORD
