Metadata-Version: 2.3
Name: nwkfmt
Version: 0.4.1
Summary: Simple Newick tree validator and formatter
Author: Cornelius Roemer
Author-email: cornelius.roemer@gmail.com
Requires-Python: >=3.11
Classifier: Programming Language :: Python :: 3
Classifier: Programming Language :: Python :: 3.11
Classifier: Programming Language :: Python :: 3.12
Classifier: Programming Language :: Python :: 3.13
Requires-Dist: biopython (>=1.73,<2.0)
Requires-Dist: typer (>=0.9.0)
